{
  "game_id": 10,
  "started_at": "2026-04-02T19:10:18",
  "players": {
    "white": "Player",
    "black": "Player"
  },
  "events": [
    {
      "type": "game_start",
      "text": "Game started",
      "players": {
        "white": "Player",
        "black": "Player"
      },
      "ts": "2026-04-02 19:10:18"
    },
    {
      "type": "move",
      "text": "[Move] №1 wP f2 -> f4; pack/effect: ні; events: —",
      "piece": "wP",
      "from": [
        5,
        1
      ],
      "to": [
        5,
        3
      ],
      "pack_effects": [],
      "events": [],
      "ts": "2026-04-02 19:10:22",
      "move": 1
    },
    {
      "type": "move",
      "text": "[Move] №2 bP d7 -> d5; pack/effect: ні; events: —",
      "piece": "bP",
      "from": [
        3,
        6
      ],
      "to": [
        3,
        4
      ],
      "pack_effects": [],
      "events": [],
      "ts": "2026-04-02 19:10:25",
      "move": 2
    },
    {
      "type": "move",
      "text": "[Move] №3 wN g1 -> f3; pack/effect: ні; events: —",
      "piece": "wN",
      "from": [
        6,
        0
      ],
      "to": [
        5,
        2
      ],
      "pack_effects": [],
      "events": [],
      "ts": "2026-04-02 19:10:26",
      "move": 3
    },
    {
      "type": "move",
      "text": "[Move] №4 bN b8 -> c6; pack/effect: ні; events: —",
      "piece": "bN",
      "from": [
        1,
        7
      ],
      "to": [
        2,
        5
      ],
      "pack_effects": [],
      "events": [],
      "ts": "2026-04-02 19:10:28",
      "move": 4
    },
    {
      "type": "move",
      "text": "[Move] №5 wN f3 -> d4; pack/effect: ні; events: —",
      "piece": "wN",
      "from": [
        5,
        2
      ],
      "to": [
        3,
        3
      ],
      "pack_effects": [],
      "events": [],
      "ts": "2026-04-02 19:10:30",
      "move": 5
    },
    {
      "type": "move",
      "text": "[Move] №6 bN c6 -> d4; pack/effect: ні; events: —",
      "piece": "bN",
      "from": [
        2,
        5
      ],
      "to": [
        3,
        3
      ],
      "pack_effects": [],
      "events": [],
      "ts": "2026-04-02 19:10:31",
      "move": 6
    },
    {
      "type": "move",
      "text": "[Move] №7 wP e2 -> e3; pack/effect: ні; events: —",
      "piece": "wP",
      "from": [
        4,
        1
      ],
      "to": [
        4,
        2
      ],
      "pack_effects": [],
      "events": [],
      "ts": "2026-04-02 19:10:33",
      "move": 7
    },
    {
      "type": "move",
      "text": "[Move] №8 bN d4 -> f3; pack/effect: ні; events: —",
      "piece": "bN",
      "from": [
        3,
        3
      ],
      "to": [
        5,
        2
      ],
      "pack_effects": [],
      "events": [],
      "ts": "2026-04-02 19:10:35",
      "move": 8
    },
    {
      "type": "move",
      "text": "[Move] №9 wP g2 -> f3; pack/effect: ні; events: —",
      "piece": "wP",
      "from": [
        6,
        1
      ],
      "to": [
        5,
        2
      ],
      "pack_effects": [],
      "events": [],
      "ts": "2026-04-02 19:10:36",
      "move": 9
    },
    {
      "type": "move",
      "text": "[Move] №10 bP e7 -> e5; pack/effect: Minesweeper DLC: Активація; events: —",
      "piece": "bP",
      "from": [
        4,
        6
      ],
      "to": [
        4,
        4
      ],
      "pack_effects": [
        "Minesweeper DLC: Активація"
      ],
      "events": [],
      "ts": "2026-04-02 19:10:39",
      "move": 10
    },
    {
      "type": "pack",
      "pack": "Minesweeper DLC",
      "pack_id": "minesweeper",
      "action": "Активація",
      "effect_id": null,
      "text": "Minesweeper DLC: Активація",
      "ts": "2026-04-02 19:10:39",
      "move": 10
    },
    {
      "type": "move",
      "text": "[Move] №11 wP f4 -> e5; pack/effect: Minesweeper DLC: Відкрити числа; events: RevealNumbers (board count:0)",
      "piece": "wP",
      "from": [
        5,
        3
      ],
      "to": [
        4,
        4
      ],
      "pack_effects": [
        "Minesweeper DLC: Відкрити числа"
      ],
      "events": [
        "RevealNumbers (board count:0)"
      ],
      "ts": "2026-04-02 19:10:41",
      "move": 11
    },
    {
      "type": "pack",
      "pack": "Minesweeper DLC",
      "pack_id": "minesweeper",
      "action": "Відкрити числа",
      "effect_id": "ms_reveal_numbers",
      "text": "Minesweeper DLC: Відкрити числа",
      "ts": "2026-04-02 19:10:41",
      "move": 11
    },
    {
      "type": "event",
      "name": "RevealNumbers",
      "event_type": "board",
      "target": [],
      "extra": "count:0",
      "text": "RevealNumbers (board count:0)",
      "ts": "2026-04-02 19:10:41",
      "move": 11
    },
    {
      "type": "move",
      "text": "[Move] №12 bP d5 -> d4; pack/effect: Minesweeper DLC: Спавн міни; events: SpawnMine (tile e7 count:1)",
      "piece": "bP",
      "from": [
        3,
        4
      ],
      "to": [
        3,
        3
      ],
      "pack_effects": [
        "Minesweeper DLC: Спавн міни"
      ],
      "events": [
        "SpawnMine (tile e7 count:1)"
      ],
      "ts": "2026-04-02 19:10:44",
      "move": 12
    },
    {
      "type": "pack",
      "pack": "Minesweeper DLC",
      "pack_id": "minesweeper",
      "action": "Спавн міни",
      "effect_id": "ms_spawn_mine",
      "text": "Minesweeper DLC: Спавн міни",
      "ts": "2026-04-02 19:10:44",
      "move": 12
    },
    {
      "type": "event",
      "name": "SpawnMine",
      "event_type": "tile",
      "target": "e7",
      "extra": "count:1",
      "text": "SpawnMine (tile e7 count:1)",
      "ts": "2026-04-02 19:10:44",
      "move": 12
    },
    {
      "type": "move",
      "text": "[Move] №13 wP e3 -> d4; pack/effect: Minesweeper DLC: Спавн мін (2-5); events: SpawnMines (tile e3,d5,g5,g4,a5 count:5)",
      "piece": "wP",
      "from": [
        4,
        2
      ],
      "to": [
        3,
        3
      ],
      "pack_effects": [
        "Minesweeper DLC: Спавн мін (2-5)"
      ],
      "events": [
        "SpawnMines (tile e3,d5,g5,g4,a5 count:5)"
      ],
      "ts": "2026-04-02 19:10:46",
      "move": 13
    },
    {
      "type": "pack",
      "pack": "Minesweeper DLC",
      "pack_id": "minesweeper",
      "action": "Спавн мін (2-5)",
      "effect_id": "ms_spawn_mines",
      "text": "Minesweeper DLC: Спавн мін (2-5)",
      "ts": "2026-04-02 19:10:46",
      "move": 13
    },
    {
      "type": "event",
      "name": "SpawnMines",
      "event_type": "tile",
      "target": "e3,d5,g5,g4,a5",
      "extra": "count:5",
      "text": "SpawnMines (tile e3,d5,g5,g4,a5 count:5)",
      "ts": "2026-04-02 19:10:46",
      "move": 13
    },
    {
      "type": "move",
      "text": "[Move] №14 bQ e8 -> a4; pack/effect: ні; events: —",
      "piece": "bQ",
      "from": [
        4,
        7
      ],
      "to": [
        0,
        3
      ],
      "pack_effects": [],
      "events": [],
      "ts": "2026-04-02 19:10:56",
      "move": 14
    },
    {
      "type": "move",
      "text": "[Move] №15 wB f1 -> c4; pack/effect: Minesweeper DLC: Спавн міни; events: SpawnMine (tile c6 count:1)",
      "piece": "wB",
      "from": [
        5,
        0
      ],
      "to": [
        2,
        3
      ],
      "pack_effects": [
        "Minesweeper DLC: Спавн міни"
      ],
      "events": [
        "SpawnMine (tile c6 count:1)"
      ],
      "ts": "2026-04-02 19:11:01",
      "move": 15
    },
    {
      "type": "pack",
      "pack": "Minesweeper DLC",
      "pack_id": "minesweeper",
      "action": "Спавн міни",
      "effect_id": "ms_spawn_mine",
      "text": "Minesweeper DLC: Спавн міни",
      "ts": "2026-04-02 19:11:01",
      "move": 15
    },
    {
      "type": "event",
      "name": "SpawnMine",
      "event_type": "tile",
      "target": "c6",
      "extra": "count:1",
      "text": "SpawnMine (tile c6 count:1)",
      "ts": "2026-04-02 19:11:01",
      "move": 15
    },
    {
      "type": "move",
      "text": "[Move] №16 bQ a4 -> b4; pack/effect: ні; events: —",
      "piece": "bQ",
      "from": [
        0,
        3
      ],
      "to": [
        1,
        3
      ],
      "pack_effects": [],
      "events": [],
      "ts": "2026-04-02 19:11:06",
      "move": 16
    },
    {
      "type": "move",
      "text": "[Move] №17 wP c2 -> c3; pack/effect: Minesweeper DLC: Спавн міни; events: SpawnMine (tile h5 count:1)",
      "piece": "wP",
      "from": [
        2,
        1
      ],
      "to": [
        2,
        2
      ],
      "pack_effects": [
        "Minesweeper DLC: Спавн міни"
      ],
      "events": [
        "SpawnMine (tile h5 count:1)"
      ],
      "ts": "2026-04-02 19:11:09",
      "move": 17
    },
    {
      "type": "pack",
      "pack": "Minesweeper DLC",
      "pack_id": "minesweeper",
      "action": "Спавн міни",
      "effect_id": "ms_spawn_mine",
      "text": "Minesweeper DLC: Спавн міни",
      "ts": "2026-04-02 19:11:09",
      "move": 17
    },
    {
      "type": "event",
      "name": "SpawnMine",
      "event_type": "tile",
      "target": "h5",
      "extra": "count:1",
      "text": "SpawnMine (tile h5 count:1)",
      "ts": "2026-04-02 19:11:09",
      "move": 17
    },
    {
      "type": "move",
      "text": "[Move] №18 bQ b4 -> b6; pack/effect: Minesweeper DLC: Спавн мін (2-5); events: SpawnMines (tile e8,f4,b4,e2,f1 count:5)",
      "piece": "bQ",
      "from": [
        1,
        3
      ],
      "to": [
        1,
        5
      ],
      "pack_effects": [
        "Minesweeper DLC: Спавн мін (2-5)"
      ],
      "events": [
        "SpawnMines (tile e8,f4,b4,e2,f1 count:5)"
      ],
      "ts": "2026-04-02 19:11:17",
      "move": 18
    },
    {
      "type": "pack",
      "pack": "Minesweeper DLC",
      "pack_id": "minesweeper",
      "action": "Спавн мін (2-5)",
      "effect_id": "ms_spawn_mines",
      "text": "Minesweeper DLC: Спавн мін (2-5)",
      "ts": "2026-04-02 19:11:17",
      "move": 18
    },
    {
      "type": "event",
      "name": "SpawnMines",
      "event_type": "tile",
      "target": "e8,f4,b4,e2,f1",
      "extra": "count:5",
      "text": "SpawnMines (tile e8,f4,b4,e2,f1 count:5)",
      "ts": "2026-04-02 19:11:17",
      "move": 18
    },
    {
      "type": "move",
      "text": "[Move] №19 wP f3 -> f4; pack/effect: ні; events: Explosion (tile f4 mine)",
      "piece": "wP",
      "from": [
        5,
        2
      ],
      "to": [
        5,
        3
      ],
      "pack_effects": [],
      "events": [
        "Explosion (tile f4 mine)"
      ],
      "ts": "2026-04-02 19:11:23",
      "move": 19
    },
    {
      "type": "event",
      "name": "Explosion",
      "event_type": "tile",
      "target": "f4",
      "extra": "mine",
      "text": "Explosion (tile f4 mine)",
      "ts": "2026-04-02 19:11:23",
      "move": 19
    },
    {
      "type": "game_over",
      "reason": "royal_captured",
      "winner": "black",
      "final_move": 19,
      "final_move_text": "[Move] №19 wP f3 -> f4; pack/effect: ні; events: Explosion (tile f4 mine)",
      "final_position": {
        "board": [
          [
            {
              "ptype": "rook",
              "color": "white",
              "gid": 17
            },
            {
              "ptype": "knight",
              "color": "white",
              "gid": 21
            },
            {
              "ptype": "bishop",
              "color": "white",
              "gid": 25
            },
            null,
            null,
            null,
            null,
            {
              "ptype": "rook",
              "color": "white",
              "gid": 18
            }
          ],
          [
            {
              "ptype": "pawn",
              "color": "white",
              "gid": 1
            },
            {
              "ptype": "pawn",
              "color": "white",
              "gid": 3
            },
            null,
            null,
            null,
            null,
            null,
            {
              "ptype": "pawn",
              "color": "white",
              "gid": 15
            }
          ],
          [
            null,
            null,
            {
              "ptype": "pawn",
              "color": "white",
              "gid": 5,
              "anchor": [
                2,
                2
              ]
            },
            null,
            null,
            null,
            null,
            null
          ],
          [
            null,
            null,
            {
              "ptype": "bishop",
              "color": "white",
              "gid": 26,
              "anchor": [
                2,
                3
              ]
            },
            null,
            null,
            null,
            null,
            null
          ],
          [
            null,
            null,
            null,
            null,
            null,
            null,
            null,
            null
          ],
          [
            null,
            {
              "ptype": "queen",
              "color": "black",
              "gid": 32,
              "anchor": [
                1,
                5
              ]
            },
            null,
            null,
            null,
            null,
            null,
            null
          ],
          [
            {
              "ptype": "pawn",
              "color": "black",
              "gid": 2
            },
            {
              "ptype": "pawn",
              "color": "black",
              "gid": 4
            },
            {
              "ptype": "pawn",
              "color": "black",
              "gid": 6
            },
            null,
            null,
            {
              "ptype": "pawn",
              "color": "black",
              "gid": 12
            },
            {
              "ptype": "pawn",
              "color": "black",
              "gid": 14
            },
            {
              "ptype": "pawn",
              "color": "black",
              "gid": 16
            }
          ],
          [
            {
              "ptype": "rook",
              "color": "black",
              "gid": 19
            },
            null,
            {
              "ptype": "bishop",
              "color": "black",
              "gid": 27
            },
            {
              "ptype": "king",
              "color": "black",
              "gid": 31
            },
            null,
            {
              "ptype": "bishop",
              "color": "black",
              "gid": 28
            },
            {
              "ptype": "knight",
              "color": "black",
              "gid": 24
            },
            {
              "ptype": "rook",
              "color": "black",
              "gid": 20
            }
          ]
        ],
        "mines": [
          [
            0,
            0,
            0,
            0,
            0,
            0,
            0,
            0
          ],
          [
            0,
            0,
            0,
            0,
            0,
            0,
            0,
            0
          ],
          [
            0,
            0,
            0,
            0,
            0,
            0,
            0,
            0
          ],
          [
            0,
            1,
            0,
            0,
            0,
            0,
            0,
            0
          ],
          [
            1,
            0,
            0,
            1,
            0,
            0,
            0,
            0
          ],
          [
            0,
            0,
            1,
            0,
            0,
            0,
            0,
            0
          ],
          [
            0,
            0,
            0,
            0,
            1,
            0,
            0,
            0
          ],
          [
            0,
            0,
            0,
            0,
            1,
            0,
            0,
            0
          ]
        ],
        "revealed": [
          [
            0,
            0,
            0,
            0,
            0,
            0,
            0,
            0
          ],
          [
            0,
            0,
            0,
            0,
            0,
            0,
            0,
            0
          ],
          [
            0,
            0,
            1,
            0,
            0,
            0,
            0,
            0
          ],
          [
            1,
            0,
            1,
            1,
            0,
            1,
            0,
            0
          ],
          [
            0,
            0,
            0,
            0,
            1,
            0,
            0,
            0
          ],
          [
            0,
            1,
            0,
            0,
            0,
            0,
            0,
            0
          ],
          [
            0,
            0,
            0,
            0,
            0,
            0,
            0,
            0
          ],
          [
            0,
            0,
            0,
            0,
            0,
            0,
            0,
            0
          ]
        ],
        "adj_counts": [
          [
            0,
            0,
            0,
            0,
            0,
            0,
            0,
            0
          ],
          [
            0,
            0,
            0,
            0,
            0,
            0,
            0,
            0
          ],
          [
            1,
            1,
            1,
            0,
            0,
            0,
            0,
            0
          ],
          [
            2,
            1,
            2,
            1,
            1,
            0,
            0,
            0
          ],
          [
            1,
            3,
            3,
            1,
            1,
            0,
            0,
            0
          ],
          [
            1,
            2,
            1,
            3,
            2,
            1,
            0,
            0
          ],
          [
            0,
            1,
            1,
            3,
            1,
            2,
            0,
            0
          ],
          [
            0,
            0,
            0,
            2,
            1,
            2,
            0,
            0
          ]
        ],
        "craters": [
          [
            7,
            4
          ],
          [
            6,
            4
          ],
          [
            4,
            2
          ],
          [
            5,
            0
          ],
          [
            5,
            3
          ],
          [
            6,
            3
          ],
          [
            4,
            1
          ]
        ],
        "chessplus_cells": [
          [
            null,
            null,
            null,
            null,
            null,
            null,
            null,
            null
          ],
          [
            null,
            null,
            null,
            null,
            null,
            null,
            null,
            null
          ],
          [
            null,
            null,
            null,
            null,
            null,
            null,
            null,
            null
          ],
          [
            null,
            null,
            null,
            null,
            null,
            null,
            null,
            null
          ],
          [
            null,
            null,
            null,
            null,
            null,
            null,
            null,
            null
          ],
          [
            null,
            null,
            null,
            null,
            null,
            null,
            null,
            null
          ],
          [
            null,
            null,
            null,
            null,
            null,
            null,
            null,
            null
          ],
          [
            null,
            null,
            null,
            null,
            null,
            null,
            null,
            null
          ]
        ],
        "chessplus_walls": [],
        "chessplus_bombs": {},
        "chessplus_void": {
          "cells": [],
          "next_expand": 0
        },
        "chessplus_mutations": {},
        "chessplus_clones": {},
        "chessplus_nukes": []
      },
      "final_score": {
        "royals": {
          "white": 0,
          "black": 2
        },
        "material": {
          "white": 23,
          "black": 34
        }
      },
      "comment": "Кінець гри: Знищені всі королівські фігури суперника. Переможець: чорний. Рахунок: королівські 0-2, матеріал 23-34.",
      "text": "Game over: royal_captured (black)",
      "ts": "2026-04-02 19:11:23"
    }
  ]
}